create_app/__init__.py
create_app/cli.py
momo/__init__.py
momo/admin.py
momo/apps.py
momo/tests.py
momo/urls.py
momo/migrations/__init__.py
momo/models/__init__.py
momo/views/__init__.py
create_app_savane-0.2.1.dist-info/METADATA
create_app_savane-0.2.1.dist-info/WHEEL
create_app_savane-0.2.1.dist-info/entry_points.txt
create_app_savane-0.2.1.dist-info/top_level.txt
create_app_savane-0.2.1.dist-info/RECORD
