Metadata-Version: 2.4
Name: create-app-savane
Version: 0.2.1
Summary: Générateur de structure d'app Django personnalisée
Author: SAVANE Mouhamed
Author-email: savanemouhamed05@gmail.com
License: MIT
Classifier: Programming Language :: Python :: 3
Classifier: Framework :: Django
Classifier: License :: OSI Approved :: MIT License
Classifier: Operating System :: OS Independent
Classifier: Intended Audience :: Developers
Classifier: Topic :: Software Development :: Code Generators
Requires-Python: >=3.6
Dynamic: author
Dynamic: author-email
Dynamic: classifier
Dynamic: description
Dynamic: description-content-type
Dynamic: license
Dynamic: requires-python
Dynamic: summary
